{"name":"Search in google","id":"buscar-en-internet;search-in-google","testSteps":[{"number":1,"description":"Given that hernan wants to search a word in google","duration":6546,"startTime":"2019-08-08T13:24:57.553-05:00[America/Bogota]","screenshots":[{"screenshot":"edbf87e3b3e6930fb052b2783857c9a0800e412302c68ac066958f03faaba326.png"}],"result":"SUCCESS","precondition":false,"children":[{"number":2,"description":"Hernan opens the Google home page","duration":5838,"startTime":"2019-08-08T13:24:57.957-05:00[America/Bogota]","screenshots":[{"screenshot":"8a1ae4cceb9dc006cd5199e993f7950472d1dc36eb3e7a8d04c71ff554c310fb.png"}],"result":"SUCCESS","precondition":false}]},{"number":3,"description":"When he search the word cheese","duration":3485,"startTime":"2019-08-08T13:25:04.100-05:00[America/Bogota]","screenshots":[{"screenshot":"8a1ae4cceb9dc006cd5199e993f7950472d1dc36eb3e7a8d04c71ff554c310fb.png"},{"screenshot":"32fbe691ab476d8db02a3f792602671ed9f4ae4932f4fc3c501b88c2c5a44499.png"}],"result":"SUCCESS","precondition":false,"children":[{"number":4,"description":"Hernan enters \u0027Quesito\u0027 into Input search","duration":818,"startTime":"2019-08-08T13:25:04.439-05:00[America/Bogota]","screenshots":[{"screenshot":"8a1ae4cceb9dc006cd5199e993f7950472d1dc36eb3e7a8d04c71ff554c310fb.png"},{"screenshot":"912f405fb8e0633b5991dacbf7f7b07416da5f1784ac4267f9f58ef9c2c2204b.png"}],"result":"SUCCESS","precondition":false},{"number":5,"description":"Hernan clicks on Button search","duration":2032,"startTime":"2019-08-08T13:25:05.260-05:00[America/Bogota]","screenshots":[{"screenshot":"912f405fb8e0633b5991dacbf7f7b07416da5f1784ac4267f9f58ef9c2c2204b.png"},{"screenshot":"32fbe691ab476d8db02a3f792602671ed9f4ae4932f4fc3c501b88c2c5a44499.png"}],"result":"SUCCESS","precondition":false}]},{"number":6,"description":"Then he should see the result in the screen","duration":1358,"startTime":"2019-08-08T13:25:07.585-05:00[America/Bogota]","screenshots":[{"screenshot":"32fbe691ab476d8db02a3f792602671ed9f4ae4932f4fc3c501b88c2c5a44499.png"}],"result":"SUCCESS","precondition":false,"children":[{"number":7,"description":"Then the result should be \u0027Quesito - Wikipedia, la enciclopedia libre\u0027","duration":631,"startTime":"2019-08-08T13:25:08.030-05:00[America/Bogota]","screenshots":[{"screenshot":"32fbe691ab476d8db02a3f792602671ed9f4ae4932f4fc3c501b88c2c5a44499.png"}],"result":"SUCCESS","precondition":false}]}],"userStory":{"id":"buscar-en-internet","storyName":"Buscar en internet","path":"src/test/resources/features/BuscarGoogle.feature","narrative":"  I want to search the word cheese in google","type":"feature"},"featureTag":{"name":"Features/Buscar en internet","type":"feature"},"title":"Search in google","tags":[{"name":"Buscar en internet","type":"feature"}],"startTime":"2019-08-08T13:24:55.987-05:00[America/Bogota]","duration":13038,"projectKey":"","sessionId":"7a6b3602efcfe07dd459c330531fdd54","driver":"chrome","manual":false,"testSource":"Cucumber","result":"SUCCESS"}